[
  {
    "name": "default",
    "type": "postgres",
    "host": "localhost",
    "synchronize": true,
    "logging": false,
    "port": 5432,
    "username": "postgres",
    "database": "postgres",
    "password": "postgres",
    "entities": ["dist/entity/**/*.js"],
    "migrations": ["dist/migration/**/*.js"],
    "subscribers": ["dist/subscriber/**/*.js"],
    "cli": {
      "entitiesDir": "src/entity",
      "migrationsDir": "src/migration",
      "subscribersDir": "src/subscriber"
    }
  }
]
